Metadata-Version: 2.1
Name: GameStateMachine
Version: 0.0.4
Summary: Game state machine - provides a game management based on a game state
Home-page: https://github.com/OleksiiBulba/GameStateManager
Author: Oleksii Bulba
Author-email: oleksii.bulba+gamestatemachine@gmail.com
Classifier: Development Status :: 2 - Pre-Alpha
Classifier: Programming Language :: Python :: 3.10
Classifier: License :: OSI Approved :: GNU General Public License v3 or later (GPLv3+)
Classifier: Operating System :: OS Independent
Classifier: Topic :: Games/Entertainment
Requires-Python: >=3.7.17
License-File: COPYING
